keywordsai_exporter_openai_agents/__init__.py
keywordsai_exporter_openai_agents/keywordsai_openai_agents_exporter.py
keywordsai_exporter_openai_agents/types.py
keywordsai_exporter_openai_agents-0.1.6.dist-info/METADATA
keywordsai_exporter_openai_agents-0.1.6.dist-info/WHEEL
keywordsai_exporter_openai_agents-0.1.6.dist-info/RECORD
